koyo/__init__.py
koyo/_version.py
koyo/audit.py
koyo/click.py
koyo/color.py
koyo/compat.py
koyo/compression.py
koyo/config.py
koyo/containers.py
koyo/context.py
koyo/dataframe.py
koyo/decorators.py
koyo/download.py
koyo/faulthandler.py
koyo/fig_mixin.py
koyo/hooks.py
koyo/image.py
koyo/json.py
koyo/json_cache.py
koyo/logging.py
koyo/mosaic.py
koyo/multicore.py
koyo/numpy.py
koyo/path.py
koyo/pdf_mixin.py
koyo/plotly.py
koyo/pptx_mixin.py
koyo/project.py
koyo/py.typed
koyo/rand.py
koyo/release.py
koyo/secret.py
koyo/sparse.py
koyo/spectrum.py
koyo/spectrum_filters.py
koyo/stats.py
koyo/system.py
koyo/timer.py
koyo/toml.py
koyo/transform.py
koyo/typing.py
koyo/utilities.py
koyo/visuals.py
koyo-0.3.1.dist-info/licenses/LICENSE
koyo-0.3.1.dist-info/METADATA
koyo-0.3.1.dist-info/WHEEL
koyo-0.3.1.dist-info/top_level.txt
koyo-0.3.1.dist-info/RECORD
