Metadata-Version: 2.4
Name: koyo
Version: 0.3.1
Summary: Simple python ulitities for various projects.
Author-email: "Lukasz G. Migas" <lukas.migas@yahoo.com>
License: BSD 3-Clause License
Project-URL: homepage, https://github.com/vandeplaslab/koyo
Project-URL: repository, https://github.com/vandeplaslab/koyo
Classifier: Development Status :: 3 - Alpha
Classifier: License :: OSI Approved :: BSD License
Classifier: Natural Language :: English
Classifier: Programming Language :: Python :: 3
Classifier: Programming Language :: Python :: 3.8
Classifier: Programming Language :: Python :: 3.9
Classifier: Programming Language :: Python :: 3.10
Classifier: Typing :: Typed
Requires-Python: >=3.8
License-File: LICENSE
Requires-Dist: numpy<2
Requires-Dist: scipy
Requires-Dist: numba
Requires-Dist: natsort
Requires-Dist: loguru
Requires-Dist: toml
Requires-Dist: click
Requires-Dist: mpire
Requires-Dist: scikit-learn
Requires-Dist: requests
Requires-Dist: tabulate
Requires-Dist: matplotlib
Requires-Dist: psutil
Requires-Dist: click-groups
Provides-Extra: pptx
Requires-Dist: python-pptx; extra == "pptx"
Requires-Dist: lxml==4.9.2; (platform_system != "Darwin" and python_version < "3.12") and extra == "pptx"
Provides-Extra: test
Requires-Dist: pytest>=6.0; extra == "test"
Requires-Dist: pytest-cov; extra == "test"
Provides-Extra: dev
Requires-Dist: black; extra == "dev"
Requires-Dist: ipython; extra == "dev"
Requires-Dist: mypy; extra == "dev"
Requires-Dist: pdbpp; extra == "dev"
Requires-Dist: pre-commit; extra == "dev"
Requires-Dist: rich; extra == "dev"
Requires-Dist: ruff; extra == "dev"
Requires-Dist: koyo[test]; extra == "dev"
Dynamic: license-file
